{
    "catInfos": [
        {
            "name": "0001",
            "themeColor": { "r": 0, "g": 0, "b": 0, "a": 255 },
            "items": [
                "Animal005",
                "Animal006",
                "Animal007"
            ]
        },
        {
            "name": "0002",
            "themeColor": { "r": 0, "g": 0, "b": 0, "a": 255 },
            "items": [
                "food002",
                "food003",
                "food004",
                "food005"
            ]
        }
    ]
}